<annotation><folder>data/images/train</folder><filename>IMG_7034_03.jpg</filename><path>C:\Users\ddela\Desktop\Projects\Machine-Learning\TensorFlow-Keras-MobileNetV2-Transfer-Learning\data\images\train\IMG_7034_03.jpg</path><source><database>Unknown</database></source><size><width>535</width><height>472</height><depth>3</depth></size><segmented>0</segmented><object><name>bottle</name><pose>Unspecified</pose><truncated>0</truncated><difficult>0</difficult><bndbox><xmin>186</xmin><ymin>144</ymin><xmax>463</xmax><ymax>285</ymax></bndbox></object></annotation>