<annotation><folder>data/images/train</folder><filename>plastic65_08.jpg</filename><path>C:\Users\ddela\Desktop\Projects\Machine-Learning\TensorFlow-Keras-MobileNetV2-Transfer-Learning\data\images\train\plastic65_08.jpg</path><source><database>Unknown</database></source><size><width>356</width><height>294</height><depth>3</depth></size><segmented>0</segmented><object><name>bottle</name><pose>Unspecified</pose><truncated>0</truncated><difficult>0</difficult><bndbox><xmin>111</xmin><ymin>120</ymin><xmax>339</xmax><ymax>293</ymax></bndbox></object></annotation>