<annotation><folder>data/images/train</folder><filename>plastic80_06.jpg</filename><path>C:\Users\ddela\Desktop\Projects\Machine-Learning\TensorFlow-Keras-MobileNetV2-Transfer-Learning\data\images\train\plastic80_06.jpg</path><source><database>Unknown</database></source><size><width>414</width><height>332</height><depth>3</depth></size><segmented>0</segmented><object><name>bottle</name><pose>Unspecified</pose><truncated>0</truncated><difficult>0</difficult><bndbox><xmin>41</xmin><ymin>40</ymin><xmax>413</xmax><ymax>279</ymax></bndbox></object></annotation>